setup.py
hyp/__init__.py
hyp/hyp.py
hyp_server.egg-info/PKG-INFO
hyp_server.egg-info/SOURCES.txt
hyp_server.egg-info/dependency_links.txt
hyp_server.egg-info/entry_points.txt
hyp_server.egg-info/top_level.txt