Metadata-Version: 1.1
Name: hyp-server
Version: 1.2.0
Summary: Hyperminimal https server
Home-page: http://github.com/rnhmjoj/hyp
Author: rnhmjoj
Author-email: micheleguerinirocco@me.com
License: MIT-GPL
Keywords: http,https,ssl,tls,upload,server
Platform: UNKNOWN
Classifier: Topic :: Internet :: WWW/HTTP :: HTTP Servers
Classifier: Topic :: Communications :: File Sharing
Classifier: Programming Language :: Python :: 3 :: Only
Classifier: License :: OSI Approved :: MIT License
Classifier: License :: OSI Approved :: GNU General Public License (GPL)
